Metadata-Version: 1.1
Name: MarkdownTools
Version: 1.0.1
Summary: Markdown processing tools, including mdmerge
Home-page: https://github.com/JeNeSuisPasDave/MarkdownTools
Author: Dave Hein
Author-email: dhein@acm.org
License: MPL-2.0
Keywords: markdown text development
Platform: UNKNOWN
Classifier: Development Status :: 5 - Production/Stable
Classifier: Intended Audience :: Developers
Classifier: Intended Audience :: End Users/Desktop
Classifier: Topic :: Text Processing :: Markup
Classifier: License :: OSI Approved :: Mozilla Public License 2.0 (MPL 2.0)
Classifier: Programming Language :: Python :: 3
Classifier: Programming Language :: Python :: 3.3
